{
  "contacts": [
    {
      "id": 145,
      "name": "json-server",
      "phone": "5855558"
    },
    [
      {
        "id": 145,
        "name": "json-server",
        "phone": "5855558"
      }
    ],
    [
      {
        "id": 145,
        "name": "json-server",
        "phone": "5855558"
      }
    ],
    [],
    [],
    [
      {
        "id": 145,
        "name": "json-server",
        "phone": "5855558"
      },
      [
        {
          "id": 145,
          "name": "json-server",
          "phone": "5855558"
        }
      ],
      [
        {
          "id": 145,
          "name": "json-server",
          "phone": "5855558"
        }
      ],
      [],
      []
    ],
    [
      [
        {
          "id": 145,
          "name": "json-server",
          "phone": "5855558"
        }
      ],
      [
        {
          "id": 145,
          "name": "json-server",
          "phone": "5855558"
        }
      ],
      [],
      []
    ],
    [],
    [
      {
        "id": 145,
        "name": "json-server",
        "phone": "5855558"
      },
      [
        {
          "id": 145,
          "name": "json-server",
          "phone": "5855558"
        }
      ],
      [
        {
          "id": 145,
          "name": "json-server",
          "phone": "5855558"
        }
      ],
      [],
      [],
      [
        {
          "id": 145,
          "name": "json-server",
          "phone": "5855558"
        },
        [
          {
            "id": 145,
            "name": "json-server",
            "phone": "5855558"
          }
        ],
        [
          {
            "id": 145,
            "name": "json-server",
            "phone": "5855558"
          }
        ],
        [],
        []
      ],
      [
        [
          {
            "id": 145,
            "name": "json-server",
            "phone": "5855558"
          }
        ],
        [
          {
            "id": 145,
            "name": "json-server",
            "phone": "5855558"
          }
        ],
        [],
        []
      ],
      []
    ]
  ]
}